{
  "hash": "14438f49",
  "configHash": "ac147f49",
  "lockfileHash": "415bb431",
  "browserHash": "99581a73",
  "optimized": {
    "vue": {
      "src": "../../../../node_modules/vue/dist/vue.runtime.esm-bundler.js",
      "file": "vue.js",
      "fileHash": "cc68b4d4",
      "needsInterop": false
    },
    "vitepress > @vue/devtools-api": {
      "src": "../../../../node_modules/.pnpm/@vue+devtools-api@7.0.25_vue@3.4.21/node_modules/@vue/devtools-api/dist/index.js",
      "file": "vitepress___@vue_devtools-api.js",
      "fileHash": "c87afe79",
      "needsInterop": false
    },
    "vitepress > @vueuse/core": {
      "src": "../../../../node_modules/.pnpm/@vueuse+core@10.9.0_vue@3.4.21/node_modules/@vueuse/core/index.mjs",
      "file": "vitepress___@vueuse_core.js",
      "fileHash": "8de62fdd",
      "needsInterop": false
    }
  },
  "chunks": {
    "chunk-CKQ4TNQ3": {
      "file": "chunk-CKQ4TNQ3.js"
    }
  }
}